anritsu_lightning/__init__.py
anritsu_lightning/common.py
anritsu_lightning/version.py
anritsu_lightning/vna37xxxd.py
anritsu_lightning-0.1.7.dist-info/LICENSE
anritsu_lightning-0.1.7.dist-info/METADATA
anritsu_lightning-0.1.7.dist-info/WHEEL
anritsu_lightning-0.1.7.dist-info/top_level.txt
anritsu_lightning-0.1.7.dist-info/RECORD
