Metadata-Version: 2.1
Name: anritsu-lightning
Version: 0.1.7
Summary: Communication with Anritsu Lightning VNA
Home-page: https://github.com/l-johnston/anritsu_lightning
Author: Lee Johnston
Author-email: lee.johnston.100@gmail.com
License: MIT
Platform: UNKNOWN
Classifier: Programming Language :: Python :: 3
Classifier: Topic :: Scientific/Engineering
Classifier: License :: OSI Approved :: MIT License
Classifier: Intended Audience :: Science/Research
Requires-Dist: pyvisa
Requires-Dist: numpy
